xsdba/__init__.py
xsdba/_adjustment.py
xsdba/_processing.py
xsdba/adjustment.py
xsdba/base.py
xsdba/cli.py
xsdba/detrending.py
xsdba/formatting.py
xsdba/loess.py
xsdba/measures.py
xsdba/nbutils.py
xsdba/options.py
xsdba/processing.py
xsdba/properties.py
xsdba/typing.py
xsdba/units.py
xsdba/utils.py
xsdba/xsdba.py
xsdba/testing/__init__.py
xsdba/testing/diagnostics.py
xsdba/testing/helpers.py
xsdba/testing/registry.txt
xsdba/testing/sdba_utils.py
xsdba/testing/utils.py
xsdba-0.4.0.dist-info/entry_points.txt
xsdba-0.4.0.dist-info/licenses/LICENSE
xsdba-0.4.0.dist-info/WHEEL
xsdba-0.4.0.dist-info/METADATA
xsdba-0.4.0.dist-info/RECORD
