Metadata-Version: 2.4
Name: xsdba
Version: 0.4.0
Summary: Statistical correction and bias adjustment tools for xarray.
Keywords: xsdba
Author-email: Éric Dupuis <dupuis.eric@ouranos.ca>, Trevor James Smith <smith.trevorj@ouranos.ca>
Maintainer-email: Éric Dupuis <dupuis.eric@ouranos.ca>, Trevor James Smith <smith.trevorj@ouranos.ca>
Requires-Python: >=3.10.0
Classifier: Development Status :: 3 - Alpha
Classifier: Intended Audience :: Developers
Classifier: License :: OSI Approved :: Apache Software License
Classifier: Natural Language :: English
Classifier: Operating System :: OS Independent
Classifier: Programming Language :: Python :: 3
Classifier: Programming Language :: Python :: 3 :: Only
Classifier: Programming Language :: Python :: 3.10
Classifier: Programming Language :: Python :: 3.11
Classifier: Programming Language :: Python :: 3.12
Classifier: Programming Language :: Python :: 3.13
Classifier: Programming Language :: Python :: Implementation :: CPython
Classifier: Topic :: Scientific/Engineering :: Information Analysis
Classifier: Topic :: Scientific/Engineering :: Mathematics
License-File: LICENSE
Requires-Dist: boltons >=20.1
Requires-Dist: bottleneck >=1.3.1
Requires-Dist: cf_xarray>=0.10.0
Requires-Dist: cftime >=1.4.1
Requires-Dist: dask[array] >=2024.8.1
Requires-Dist: filelock >=3.14.0
Requires-Dist: jsonpickle >=3.1.0
Requires-Dist: numba >=0.57.0
Requires-Dist: numpy >=1.24.0
Requires-Dist: packaging
Requires-Dist: pandas >=2.2.0
Requires-Dist: pint>=0.24.4
Requires-Dist: scipy >=1.11.0
Requires-Dist: statsmodels >=0.14.2
Requires-Dist: typer >=0.12.3
Requires-Dist: xarray >=2023.11.0
Requires-Dist: xsdba[dev] ; extra == "all"
Requires-Dist: xsdba[docs] ; extra == "all"
Requires-Dist: xsdba[extras] ; extra == "all"
Requires-Dist: black ==25.1.0 ; extra == "dev"
Requires-Dist: blackdoc ==0.3.9 ; extra == "dev"
Requires-Dist: bump-my-version >=0.30.1 ; extra == "dev"
Requires-Dist: codespell >=2.4.1 ; extra == "dev"
Requires-Dist: coverage >=7.5.0 ; extra == "dev"
Requires-Dist: deptry >=0.23.0 ; extra == "dev"
Requires-Dist: flake8 >=7.1.1 ; extra == "dev"
Requires-Dist: flake8-rst-docstrings >=0.3.0 ; extra == "dev"
Requires-Dist: flit >=3.10.1,<4.0 ; extra == "dev"
Requires-Dist: h5netcdf >=1.3.0 ; extra == "dev"
Requires-Dist: isort ==6.0.1 ; extra == "dev"
Requires-Dist: mypy >=1.14.1 ; extra == "dev"
Requires-Dist: matplotlib >=3.6.0 ; extra == "dev"
Requires-Dist: numpydoc >=1.8.0 ; extra == "dev"
Requires-Dist: pip >=25.0 ; extra == "dev"
Requires-Dist: pooch >=1.8.0 ; extra == "dev"
Requires-Dist: pre-commit >=3.5.0 ; extra == "dev"
Requires-Dist: pytest >=8.0.0,<9.0.0 ; extra == "dev"
Requires-Dist: pytest-cov >=5.0.0 ; extra == "dev"
Requires-Dist: pytest-xdist >=3.2.0 ; extra == "dev"
Requires-Dist: ruff >=0.9.0 ; extra == "dev"
Requires-Dist: tox >=4.24.1 ; extra == "dev"
Requires-Dist: vulture >=2.14 ; extra == "dev"
Requires-Dist: watchdog >=4.0.0 ; extra == "dev"
Requires-Dist: xdoctest >=1.1.5 ; extra == "dev"
Requires-Dist: yamllint >=1.35.1 ; extra == "dev"
Requires-Dist: furo >=2023.9.10 ; extra == "docs"
Requires-Dist: ipykernel ; extra == "docs"
Requires-Dist: ipython >=8.5.0 ; extra == "docs"
Requires-Dist: jupyter_client ; extra == "docs"
Requires-Dist: matplotlib >=3.6.0 ; extra == "docs"
Requires-Dist: nbsphinx >=0.9.7 ; extra == "docs"
Requires-Dist: nc-time-axis >=1.4.1 ; extra == "docs"
Requires-Dist: pooch >=1.8.0 ; extra == "docs"
Requires-Dist: pygments ; extra == "docs"
Requires-Dist: sphinx >=8.2.2 ; extra == "docs"
Requires-Dist: sphinx-autobuild >=2024.4.16 ; extra == "docs"
Requires-Dist: sphinx-autodoc-typehints >=3.1.0 ; extra == "docs"
Requires-Dist: sphinx-codeautolink >=0.16.2 ; extra == "docs"
Requires-Dist: sphinx-copybutton ; extra == "docs"
Requires-Dist: sphinx-intl ; extra == "docs"
Requires-Dist: sphinx-mdinclude ; extra == "docs"
Requires-Dist: sphinxcontrib-bibtex ; extra == "docs"
Requires-Dist: fastnanquantile >=0.0.2 ; extra == "extras"
Requires-Dist: POT >=0.9.4 ; extra == "extras"
Requires-Dist: xclim >=0.56.0 ; extra == "extras"
Project-URL: About Ouranos, https://ouranos.ca/en/
Project-URL: Changelog, https://xsdba.readthedocs.io/en/stable/changelog.html
Project-URL: Homepage, https://xsdba.readthedocs.io/
Project-URL: Issue tracker, https://github.com/Ouranosinc/xsdba/issues
Project-URL: Source, https://github.com/Ouranosinc/xsdba
Provides-Extra: all
Provides-Extra: dev
Provides-Extra: docs
Provides-Extra: extras
